{
    "chunk_id": "81ca7fa1-d52e-4c9a-ae88-b923073192c6",
    "source_database": "ICMR",
    "document_title": "ICMR_NIN_Dietary_Guidelines_Real.pdf",
    "publication_version": "Latest",
    "chunk_sequence_number": 246,
    "content_type": "Medical Guideline",
    "language": "English",
    "text": "foods. /c185Limit consumption of sugar and unhealthy processed foods which provide only (empty) calories. /c185Prefer fortified processed foods. /c185Always read food labels (given on containers) regarding content of nutrients, shelf-life and the additives present. /c185POINTS TO PONDER 79 Guideline 15 Who is an elderly person? How are the elderly different? Include micronutrient rich foods in the diets of elderly people to enable them to be fit and active Rationale: /c247Body composition changes with advancing age, and these changes affect nutritional needs of the elderly. /c247Elderly or aged people require reduced amounts of calories, as their lean muscle mass and physical activity decrease with ageing. /c247Elderly are more prone to diseases due to lowered food intake, physical"
}